espuma/__init__.py
espuma/base.py
espuma/boundary_probe.py
espuma-0.0.16.dist-info/METADATA
espuma-0.0.16.dist-info/WHEEL
espuma-0.0.16.dist-info/licenses/LICENSE
espuma-0.0.16.dist-info/RECORD
